[
  {
    "word": "epistemology",
    "phonetic": "/ɪˌpɪstɪˈmɒlədʒi/",
    "meaning": "认识论",
    "pos": "n.",
    "band": 9,
    "topic": "education",
    "example": "The epistemology of scientific inquiry has been debated by philosophers for centuries.",
    "example_cn": "科学探究的认识论几个世纪以来一直被哲学家们所争论。",
    "collocations": ["social epistemology", "epistemology of science"],
    "synonyms": ["theory of knowledge", "philosophy of knowledge"],
    "etymology": "episteme (知识) + -ology (学科) → 关于知识的学科 → 认识论"
  },
  {
    "word": "autodidactic",
    "phonetic": "/ˌɔːtəʊdaɪˈdæktɪk/",
    "meaning": "自学的",
    "pos": "adj.",
    "band": 9,
    "topic": "education",
    "example": "His autodidactic approach to mastering several languages impressed the admissions panel.",
    "example_cn": "他自学掌握多门语言的方法给招生委员会留下了深刻印象。",
    "collocations": ["autodidactic learner", "autodidactic approach"],
    "synonyms": ["self-taught", "self-educated"],
    "etymology": "auto- (自己) + didact (教) + -ic → 自己教自己的 → 自学的"
  },
  {
    "word": "pedantic",
    "phonetic": "/pɪˈdæntɪk/",
    "meaning": "学究式的，迂腐的",
    "pos": "adj.",
    "band": 9,
    "topic": "education",
    "example": "The professor's pedantic insistence on citation formats frustrated many students.",
    "example_cn": "教授对引用格式学究式的坚持让许多学生感到沮丧。",
    "collocations": ["pedantic approach", "pedantic attention to detail"],
    "synonyms": ["meticulous", "fastidious", "doctrinaire"],
    "etymology": "pedant (学究) + -ic → 学究般的 → 迂腐的"
  },
  {
    "word": "heuristic",
    "phonetic": "/hjʊˈrɪstɪk/",
    "meaning": "启发式的",
    "pos": "adj./n.",
    "band": 9,
    "topic": "education",
    "example": "Teachers should adopt heuristic methods that encourage students to discover solutions independently.",
    "example_cn": "教师应采用启发式方法，鼓励学生独立发现解决方案。",
    "collocations": ["heuristic method", "heuristic approach"],
    "synonyms": ["exploratory", "investigative", "discovery-based"],
    "etymology": "希腊语 heuriskein (发现) → 通过发现来学习 → 启发式的"
  },
  {
    "word": "didacticism",
    "phonetic": "/daɪˈdæktɪsɪzəm/",
    "meaning": "说教主义",
    "pos": "n.",
    "band": 9,
    "topic": "education",
    "example": "Excessive didacticism in the classroom can stifle students' creative thinking.",
    "example_cn": "课堂上过度的说教主义会扼杀学生的创造性思维。",
    "collocations": ["moral didacticism", "excessive didacticism"],
    "synonyms": ["preachiness", "moralising", "sermonising"],
    "etymology": "didact (教) + -icism (主义) → 教导的主义 → 说教主义"
  },
  {
    "word": "peripatetic",
    "phonetic": "/ˌperɪpəˈtetɪk/",
    "meaning": "巡回的，游历的",
    "pos": "adj.",
    "band": 9,
    "topic": "education",
    "example": "The peripatetic lecturer travels between three universities to deliver seminars.",
    "example_cn": "这位巡回讲师在三所大学之间奔波进行授课。",
    "collocations": ["peripatetic lifestyle", "peripatetic teacher"],
    "synonyms": ["itinerant", "nomadic", "travelling"],
    "etymology": "peri- (周围) + patein (行走) → 四处行走的 → 巡回的"
  },
  {
    "word": "scholastic",
    "phonetic": "/skəˈlæstɪk/",
    "meaning": "学术的，学院的",
    "pos": "adj.",
    "band": 9,
    "topic": "education",
    "example": "Her scholastic achievements earned her a prestigious fellowship at Oxford.",
    "example_cn": "她的学术成就使她获得了牛津大学的知名奖学金。",
    "collocations": ["scholastic achievement", "scholastic aptitude"],
    "synonyms": ["academic", "intellectual", "scholarly"],
    "etymology": "schola (学校) + -astic → 与学校相关的 → 学术的"
  },
  {
    "word": "teleological",
    "phonetic": "/ˌteliəˈlɒdʒɪkəl/",
    "meaning": "目的论的",
    "pos": "adj.",
    "band": 9,
    "topic": "education",
    "example": "A teleological view of education sees learning as directed towards a specific moral purpose.",
    "example_cn": "目的论的教育观认为学习是朝着特定道德目标前进的。",
    "collocations": ["teleological argument", "teleological perspective"],
    "synonyms": ["purposive", "goal-oriented", "finalistic"],
    "etymology": "telos (目的) + -logical (学说的) → 关于目的的学说 → 目的论的"
  },
  {
    "word": "hermeneutic",
    "phonetic": "/ˌhɜːmɪˈnjuːtɪk/",
    "meaning": "诠释学的",
    "pos": "adj.",
    "band": 9,
    "topic": "education",
    "example": "A hermeneutic approach to reading encourages deeper interpretation of literary texts.",
    "example_cn": "诠释学的阅读方法鼓励对文学文本进行更深层次的解读。",
    "collocations": ["hermeneutic circle", "hermeneutic approach"],
    "synonyms": ["interpretive", "exegetical", "analytical"],
    "etymology": "Hermes (赫尔墨斯，信使之神) + -eutic → 解释神意 → 诠释学的"
  },
  {
    "word": "Socratic",
    "phonetic": "/səˈkrætɪk/",
    "meaning": "苏格拉底式的，启发式问答的",
    "pos": "adj.",
    "band": 9,
    "topic": "education",
    "example": "The Socratic method of teaching involves asking probing questions to stimulate critical thinking.",
    "example_cn": "苏格拉底式教学法通过提出探究性问题来激发批判性思维。",
    "collocations": ["Socratic method", "Socratic dialogue"],
    "synonyms": ["dialectical", "questioning", "interrogative"],
    "etymology": "源自古希腊哲学家 Socrates (苏格拉底) 的问答式教学法"
  },
  {
    "word": "anthropocene",
    "phonetic": "/ˈænθrəpəˌsiːn/",
    "meaning": "人类世",
    "pos": "n.",
    "band": 9,
    "topic": "environment",
    "example": "Many scientists argue that we have entered the Anthropocene, an era defined by human impact on the planet.",
    "example_cn": "许多科学家认为我们已进入人类世——一个以人类对地球影响为标志的时代。",
    "collocations": ["Anthropocene era", "Anthropocene epoch"],
    "synonyms": ["human epoch", "age of humans"],
    "etymology": "anthropo- (人类) + -cene (新的，地质纪) → 人类的地质纪 → 人类世"
  },
  {
    "word": "sequestration",
    "phonetic": "/ˌsiːkwɪˈstreɪʃən/",
    "meaning": "封存，隔离",
    "pos": "n.",
    "band": 9,
    "topic": "environment",
    "example": "Carbon sequestration technologies could play a vital role in mitigating climate change.",
    "example_cn": "碳封存技术可能在缓解气候变化方面发挥至关重要的作用。",
    "collocations": ["carbon sequestration", "geological sequestration"],
    "synonyms": ["capture", "isolation", "storage"],
    "etymology": "sequestr- (隔离) + -ation → 隔离的过程 → 封存"
  },
  {
    "word": "xerophytic",
    "phonetic": "/ˌzɪərəˈfɪtɪk/",
    "meaning": "旱生的，耐旱植物的",
    "pos": "adj.",
    "band": 9,
    "topic": "environment",
    "example": "Xerophytic vegetation has evolved remarkable adaptations to survive in arid conditions.",
    "example_cn": "旱生植被已进化出非凡的适应能力以在干旱条件下存活。",
    "collocations": ["xerophytic plants", "xerophytic adaptation"],
    "synonyms": ["drought-resistant", "arid-adapted"],
    "etymology": "xero- (干燥) + phyt (植物) + -ic → 干燥植物的 → 旱生的"
  },
  {
    "word": "oligotrophic",
    "phonetic": "/ˌɒlɪɡəˈtrɒfɪk/",
    "meaning": "贫营养的",
    "pos": "adj.",
    "band": 9,
    "topic": "environment",
    "example": "Oligotrophic lakes have very low nutrient levels but exceptionally clear water.",
    "example_cn": "贫营养湖泊营养水平极低，但水质异常清澈。",
    "collocations": ["oligotrophic lake", "oligotrophic conditions"],
    "synonyms": ["nutrient-poor", "infertile"],
    "etymology": "oligo- (少) + troph (营养) + -ic → 营养少的 → 贫营养的"
  },
  {
    "word": "symbiotic",
    "phonetic": "/ˌsɪmbaɪˈɒtɪk/",
    "meaning": "共生的",
    "pos": "adj.",
    "band": 9,
    "topic": "environment",
    "example": "The symbiotic relationship between coral and algae is threatened by rising ocean temperatures.",
    "example_cn": "珊瑚与藻类之间的共生关系正受到海洋温度上升的威胁。",
    "collocations": ["symbiotic relationship", "symbiotic interaction"],
    "synonyms": ["mutualistic", "cooperative", "interdependent"],
    "etymology": "sym- (一起) + bio (生命) + -tic → 一起生活的 → 共生的"
  },
  {
    "word": "phytoremediation",
    "phonetic": "/ˌfaɪtəʊrɪˌmiːdiˈeɪʃən/",
    "meaning": "植物修复",
    "pos": "n.",
    "band": 9,
    "topic": "environment",
    "example": "Phytoremediation uses plants to absorb heavy metals and decontaminate polluted soil.",
    "example_cn": "植物修复利用植物吸收重金属并净化受污染的土壤。",
    "collocations": ["phytoremediation techniques", "phytoremediation of soil"],
    "synonyms": ["bioremediation", "botanical cleanup"],
    "etymology": "phyto- (植物) + remediation (修复) → 用植物修复 → 植物修复"
  },
  {
    "word": "stratospheric",
    "phonetic": "/ˌstrætəˈsferɪk/",
    "meaning": "平流层的；极高的",
    "pos": "adj.",
    "band": 9,
    "topic": "environment",
    "example": "Stratospheric ozone depletion remains one of the most critical environmental challenges.",
    "example_cn": "平流层臭氧消耗仍然是最严峻的环境挑战之一。",
    "collocations": ["stratospheric ozone", "stratospheric temperatures"],
    "synonyms": ["atmospheric", "upper-atmospheric", "sky-high"],
    "etymology": "strato- (层) + spher (球) + -ic → 层球的 → 平流层的"
  },
  {
    "word": "biogeochemical",
    "phonetic": "/ˌbaɪəʊˌdʒiːəʊˈkemɪkəl/",
    "meaning": "生物地球化学的",
    "pos": "adj.",
    "band": 9,
    "topic": "environment",
    "example": "Human activities have severely disrupted biogeochemical cycles such as the nitrogen and carbon cycles.",
    "example_cn": "人类活动严重破坏了氮循环和碳循环等生物地球化学循环。",
    "collocations": ["biogeochemical cycle", "biogeochemical processes"],
    "synonyms": ["geochemical", "ecological-chemical"],
    "etymology": "bio- (生命) + geo- (地球) + chemical (化学的) → 生物地球化学的"
  },
  {
    "word": "autotrophic",
    "phonetic": "/ˌɔːtəˈtrɒfɪk/",
    "meaning": "自养的",
    "pos": "adj.",
    "band": 9,
    "topic": "environment",
    "example": "Autotrophic organisms form the base of virtually all food chains on Earth.",
    "example_cn": "自养生物构成了地球上几乎所有食物链的基础。",
    "collocations": ["autotrophic organisms", "autotrophic nutrition"],
    "synonyms": ["self-nourishing", "self-feeding"],
    "etymology": "auto- (自己) + troph (营养) + -ic → 自己提供营养的 → 自养的"
  },
  {
    "word": "cryogenic",
    "phonetic": "/ˌkraɪəˈdʒenɪk/",
    "meaning": "低温的，冷冻的",
    "pos": "adj.",
    "band": 9,
    "topic": "environment",
    "example": "Cryogenic preservation of permafrost samples allows scientists to study ancient climate conditions.",
    "example_cn": "对永久冻土样本的低温保存使科学家能够研究古代气候条件。",
    "collocations": ["cryogenic temperatures", "cryogenic storage"],
    "synonyms": ["ultra-cold", "freezing", "sub-zero"],
    "etymology": "cryo- (冷) + -genic (产生) → 产生极低温的 → 低温的"
  },
  {
    "word": "ubiquitous",
    "phonetic": "/juːˈbɪkwɪtəs/",
    "meaning": "无处不在的",
    "pos": "adj.",
    "band": 9,
    "topic": "technology",
    "example": "Smartphones have become so ubiquitous that they are now considered essential tools for daily life.",
    "example_cn": "智能手机已变得无处不在，如今被视为日常生活的必备工具。",
    "collocations": ["ubiquitous computing", "ubiquitous presence"],
    "synonyms": ["omnipresent", "pervasive", "universal"],
    "etymology": "ubique (到处) + -ous → 到处都有的 → 无处不在的"
  },
  {
    "word": "algorithmic",
    "phonetic": "/ˌælɡəˈrɪðmɪk/",
    "meaning": "算法的",
    "pos": "adj.",
    "band": 9,
    "topic": "technology",
    "example": "Algorithmic bias in hiring software can perpetuate existing social inequalities.",
    "example_cn": "招聘软件中的算法偏见可能会使现有的社会不平等持续存在。",
    "collocations": ["algorithmic bias", "algorithmic decision-making"],
    "synonyms": ["computational", "programmatic", "automated"],
    "etymology": "源自波斯数学家 al-Khwarizmi 之名 → 运算步骤 → 算法的"
  },
  {
    "word": "cryptographic",
    "phonetic": "/ˌkrɪptəˈɡræfɪk/",
    "meaning": "密码学的，加密的",
    "pos": "adj.",
    "band": 9,
    "topic": "technology",
    "example": "Cryptographic protocols are essential for securing sensitive data transmitted over the internet.",
    "example_cn": "密码学协议对于保护通过互联网传输的敏感数据至关重要。",
    "collocations": ["cryptographic encryption", "cryptographic key"],
    "synonyms": ["encrypted", "cipher-based", "coded"],
    "etymology": "crypto- (隐藏) + graph (写) + -ic → 隐秘书写的 → 加密的"
  },
  {
    "word": "proprietary",
    "phonetic": "/prəˈpraɪətəri/",
    "meaning": "专有的，专利的",
    "pos": "adj.",
    "band": 9,
    "topic": "technology",
    "example": "Many tech companies rely on proprietary software to maintain their competitive advantage.",
    "example_cn": "许多科技公司依赖专有软件来维持竞争优势。",
    "collocations": ["proprietary software", "proprietary technology"],
    "synonyms": ["patented", "exclusive", "copyrighted"],
    "etymology": "proprietor (所有者) + -ary → 属于所有者的 → 专有的"
  },
  {
    "word": "deterministic",
    "phonetic": "/dɪˌtɜːmɪˈnɪstɪk/",
    "meaning": "确定性的",
    "pos": "adj.",
    "band": 9,
    "topic": "technology",
    "example": "Unlike deterministic models, machine learning systems can produce variable outputs for identical inputs.",
    "example_cn": "与确定性模型不同，机器学习系统对相同输入可能产生不同输出。",
    "collocations": ["deterministic algorithm", "deterministic model"],
    "synonyms": ["predictable", "fixed", "predetermined"],
    "etymology": "determine (决定) + -istic → 可被决定的 → 确定性的"
  },
  {
    "word": "asynchronous",
    "phonetic": "/eɪˈsɪŋkrənəs/",
    "meaning": "异步的",
    "pos": "adj.",
    "band": 9,
    "topic": "technology",
    "example": "Asynchronous communication tools enable remote teams to collaborate across different time zones.",
    "example_cn": "异步通信工具使远程团队能够跨时区协作。",
    "collocations": ["asynchronous communication", "asynchronous processing"],
    "synonyms": ["non-simultaneous", "non-synchronised"],
    "etymology": "a- (不) + syn- (同) + chrono (时间) + -ous → 不同时的 → 异步的"
  },
  {
    "word": "decentralised",
    "phonetic": "/diːˈsentrəlaɪzd/",
    "meaning": "去中心化的",
    "pos": "adj.",
    "band": 9,
    "topic": "technology",
    "example": "Decentralised networks eliminate the need for a single controlling authority.",
    "example_cn": "去中心化网络消除了对单一控制机构的需求。",
    "collocations": ["decentralised system", "decentralised governance"],
    "synonyms": ["distributed", "dispersed", "devolved"],
    "etymology": "de- (去除) + central (中心) + -ised → 去除中心的 → 去中心化的"
  },
  {
    "word": "interoperable",
    "phonetic": "/ˌɪntərˈɒpərəbəl/",
    "meaning": "可互操作的",
    "pos": "adj.",
    "band": 9,
    "topic": "technology",
    "example": "Healthcare systems must become interoperable so that patient records can be shared seamlessly.",
    "example_cn": "医疗系统必须实现互操作性，以便患者记录能够无缝共享。",
    "collocations": ["interoperable systems", "interoperable standards"],
    "synonyms": ["compatible", "interconnectable", "cross-functional"],
    "etymology": "inter- (相互) + operable (可操作的) → 可相互操作的"
  },
  {
    "word": "quantum",
    "phonetic": "/ˈkwɒntəm/",
    "meaning": "量子的；巨大的飞跃",
    "pos": "adj./n.",
    "band": 9,
    "topic": "technology",
    "example": "Quantum computing promises to solve complex problems that are intractable for classical computers.",
    "example_cn": "量子计算有望解决经典计算机无法处理的复杂问题。",
    "collocations": ["quantum computing", "quantum leap"],
    "synonyms": ["subatomic", "revolutionary"],
    "etymology": "拉丁语 quantum (多少) → 最小离散单位 → 量子"
  },
  {
    "word": "exponential",
    "phonetic": "/ˌekspəˈnenʃəl/",
    "meaning": "指数级的",
    "pos": "adj.",
    "band": 9,
    "topic": "technology",
    "example": "The exponential growth of data has created unprecedented challenges for storage and privacy.",
    "example_cn": "数据的指数级增长为存储和隐私带来了前所未有的挑战。",
    "collocations": ["exponential growth", "exponential increase"],
    "synonyms": ["rapid", "accelerating", "geometric"],
    "etymology": "exponent (指数) + -ial → 如指数般增长的 → 指数级的"
  },
  {
    "word": "iatrogenic",
    "phonetic": "/aɪˌætrəˈdʒenɪk/",
    "meaning": "医源性的",
    "pos": "adj.",
    "band": 9,
    "topic": "health",
    "example": "Iatrogenic infections acquired in hospitals remain a significant public health concern.",
    "example_cn": "在医院获得的医源性感染仍然是一个重大的公共卫生问题。",
    "collocations": ["iatrogenic infection", "iatrogenic disease"],
    "synonyms": ["medically-induced", "treatment-caused"],
    "etymology": "iatro- (医生) + -genic (产生的) → 由医生引起的 → 医源性的"
  },
  {
    "word": "idiopathic",
    "phonetic": "/ˌɪdiəˈpæθɪk/",
    "meaning": "特发性的，原因不明的",
    "pos": "adj.",
    "band": 9,
    "topic": "health",
    "example": "The patient was diagnosed with idiopathic pulmonary fibrosis, a condition with no known cause.",
    "example_cn": "患者被诊断出特发性肺纤维化，这是一种病因不明的疾病。",
    "collocations": ["idiopathic disease", "idiopathic condition"],
    "synonyms": ["unexplained", "cryptogenic", "of unknown origin"],
    "etymology": "idio- (自身的) + path (疾病) + -ic → 自身产生的疾病 → 特发性的"
  },
  {
    "word": "aetiology",
    "phonetic": "/ˌiːtiˈɒlədʒi/",
    "meaning": "病因学",
    "pos": "n.",
    "band": 9,
    "topic": "health",
    "example": "Understanding the aetiology of chronic diseases is crucial for developing effective prevention strategies.",
    "example_cn": "了解慢性病的病因学对于制定有效的预防策略至关重要。",
    "collocations": ["disease aetiology", "aetiology of cancer"],
    "synonyms": ["causation", "pathogenesis", "origin"],
    "etymology": "aitia (原因) + -ology (学科) → 研究原因的学科 → 病因学"
  },
  {
    "word": "nosocomial",
    "phonetic": "/ˌnɒsəˈkəʊmiəl/",
    "meaning": "院内感染的",
    "pos": "adj.",
    "band": 9,
    "topic": "health",
    "example": "Strict hygiene protocols are essential for reducing nosocomial infections in intensive care units.",
    "example_cn": "严格的卫生规程对于减少重症监护室的院内感染至关重要。",
    "collocations": ["nosocomial infection", "nosocomial transmission"],
    "synonyms": ["hospital-acquired", "healthcare-associated"],
    "etymology": "noso- (疾病) + com (照顾) + -ial → 在照顾疾病的地方产生的 → 院内感染的"
  },
  {
    "word": "pharmacokinetic",
    "phonetic": "/ˌfɑːməkəʊkɪˈnetɪk/",
    "meaning": "药代动力学的",
    "pos": "adj.",
    "band": 9,
    "topic": "health",
    "example": "Pharmacokinetic studies determine how quickly a drug is absorbed and metabolised by the body.",
    "example_cn": "药代动力学研究确定药物被身体吸收和代谢的速度。",
    "collocations": ["pharmacokinetic profile", "pharmacokinetic analysis"],
    "synonyms": ["drug metabolism", "biokinetic"],
    "etymology": "pharma (药) + kinetic (运动的) → 药物在体内运动 → 药代动力学的"
  },
  {
    "word": "psychotropic",
    "phonetic": "/ˌsaɪkəˈtrɒpɪk/",
    "meaning": "精神药物的，影响精神的",
    "pos": "adj.",
    "band": 9,
    "topic": "health",
    "example": "The overprescription of psychotropic medication to children has sparked heated ethical debate.",
    "example_cn": "对儿童过度处方精神药物引发了激烈的伦理争论。",
    "collocations": ["psychotropic drugs", "psychotropic medication"],
    "synonyms": ["psychoactive", "mind-altering", "neuroactive"],
    "etymology": "psycho- (精神) + tropic (转向) → 转向精神的 → 影响精神的"
  },
  {
    "word": "asymptomatic",
    "phonetic": "/ˌeɪsɪmptəˈmætɪk/",
    "meaning": "无症状的",
    "pos": "adj.",
    "band": 9,
    "topic": "health",
    "example": "Asymptomatic carriers can unknowingly transmit infectious diseases to vulnerable populations.",
    "example_cn": "无症状携带者可能在不知情的情况下将传染病传播给易感人群。",
    "collocations": ["asymptomatic carrier", "asymptomatic infection"],
    "synonyms": ["symptom-free", "subclinical", "latent"],
    "etymology": "a- (无) + symptom (症状) + -atic → 没有症状的 → 无症状的"
  },
  {
    "word": "teratogenic",
    "phonetic": "/ˌterətəˈdʒenɪk/",
    "meaning": "致畸的",
    "pos": "adj.",
    "band": 9,
    "topic": "health",
    "example": "Pregnant women are warned to avoid teratogenic substances that could harm foetal development.",
    "example_cn": "孕妇被警告避免接触可能损害胎儿发育的致畸物质。",
    "collocations": ["teratogenic effects", "teratogenic agents"],
    "synonyms": ["birth-defect-causing", "embryotoxic"],
    "etymology": "terat- (怪物/畸形) + -genic (产生) → 产生畸形的 → 致畸的"
  },
  {
    "word": "autoimmune",
    "phonetic": "/ˌɔːtəʊɪˈmjuːn/",
    "meaning": "自身免疫的",
    "pos": "adj.",
    "band": 9,
    "topic": "health",
    "example": "Autoimmune disorders occur when the body's immune system mistakenly attacks its own healthy tissues.",
    "example_cn": "自身免疫性疾病发生在身体的免疫系统错误地攻击自身健康组织时。",
    "collocations": ["autoimmune disease", "autoimmune response"],
    "synonyms": ["self-immune", "immune-mediated"],
    "etymology": "auto- (自身) + immune (免疫) → 对自身的免疫反应 → 自身免疫的"
  },
  {
    "word": "hegemony",
    "phonetic": "/hɪˈdʒeməni/",
    "meaning": "霸权，领导权",
    "pos": "n.",
    "band": 9,
    "topic": "society",
    "example": "The country's cultural hegemony has shaped global media consumption patterns for decades.",
    "example_cn": "该国的文化霸权几十年来一直塑造着全球的媒体消费模式。",
    "collocations": ["cultural hegemony", "political hegemony"],
    "synonyms": ["dominance", "supremacy", "predominance"],
    "etymology": "希腊语 hegemon (领导者) → 统治地位 → 霸权"
  },
  {
    "word": "oligarchy",
    "phonetic": "/ˈɒlɪɡɑːki/",
    "meaning": "寡头政治",
    "pos": "n.",
    "band": 9,
    "topic": "society",
    "example": "Critics argue that the concentration of wealth has transformed the democracy into an oligarchy.",
    "example_cn": "批评者认为财富集中已将民主制度转变为寡头政治。",
    "collocations": ["ruling oligarchy", "corporate oligarchy"],
    "synonyms": ["plutocracy", "aristocracy", "elite rule"],
    "etymology": "oligo- (少数) + -archy (统治) → 少数人的统治 → 寡头政治"
  },
  {
    "word": "antithetical",
    "phonetic": "/ˌæntɪˈθetɪkəl/",
    "meaning": "对立的，截然相反的",
    "pos": "adj.",
    "band": 9,
    "topic": "society",
    "example": "The values of rampant consumerism are antithetical to the principles of environmental sustainability.",
    "example_cn": "肆意消费主义的价值观与环境可持续发展的原则截然对立。",
    "collocations": ["antithetical to", "diametrically antithetical"],
    "synonyms": ["opposite", "contrary", "contradictory"],
    "etymology": "anti- (反) + thesis (论点) + -ical → 反论点的 → 对立的"
  },
  {
    "word": "Machiavellian",
    "phonetic": "/ˌmækiəˈveliən/",
    "meaning": "马基雅维利式的，权谋的",
    "pos": "adj.",
    "band": 9,
    "topic": "society",
    "example": "His Machiavellian tactics of manipulation and deceit ultimately alienated his closest allies.",
    "example_cn": "他马基雅维利式的操纵和欺骗手段最终疏远了他最亲密的盟友。",
    "collocations": ["Machiavellian tactics", "Machiavellian politics"],
    "synonyms": ["cunning", "scheming", "unscrupulous"],
    "etymology": "源自意大利政治家 Machiavelli (马基雅维利) 的权术思想"
  },
  {
    "word": "zeitgeist",
    "phonetic": "/ˈzaɪtɡaɪst/",
    "meaning": "时代精神",
    "pos": "n.",
    "band": 9,
    "topic": "society",
    "example": "The environmental movement perfectly captures the zeitgeist of the twenty-first century.",
    "example_cn": "环保运动完美地捕捉了二十一世纪的时代精神。",
    "collocations": ["cultural zeitgeist", "capture the zeitgeist"],
    "synonyms": ["spirit of the age", "ethos", "mood of the times"],
    "etymology": "德语 Zeit (时代) + Geist (精神) → 时代精神"
  },
  {
    "word": "parochial",
    "phonetic": "/pəˈrəʊkiəl/",
    "meaning": "狭隘的，目光短浅的",
    "pos": "adj.",
    "band": 9,
    "topic": "society",
    "example": "A parochial worldview prevents individuals from appreciating the complexities of global issues.",
    "example_cn": "狭隘的世界观使人们无法理解全球问题的复杂性。",
    "collocations": ["parochial attitude", "parochial interests"],
    "synonyms": ["narrow-minded", "insular", "provincial"],
    "etymology": "parochia (教区) + -al → 局限于教区的 → 狭隘的"
  },
  {
    "word": "anachronistic",
    "phonetic": "/əˌnækrəˈnɪstɪk/",
    "meaning": "过时的，不合时代的",
    "pos": "adj.",
    "band": 9,
    "topic": "society",
    "example": "Many argue that the monarchy is an anachronistic institution in a modern democratic society.",
    "example_cn": "许多人认为君主制在现代民主社会中是一种过时的制度。",
    "collocations": ["anachronistic institution", "seem anachronistic"],
    "synonyms": ["outdated", "archaic", "obsolete"],
    "etymology": "ana- (逆) + chron (时间) + -istic → 逆时间的 → 不合时代的"
  },
  {
    "word": "draconian",
    "phonetic": "/drəˈkəʊniən/",
    "meaning": "严苛的，严厉的",
    "pos": "adj.",
    "band": 9,
    "topic": "society",
    "example": "The government introduced draconian measures to suppress political dissent.",
    "example_cn": "政府采取了严苛的措施来压制政治异见。",
    "collocations": ["draconian measures", "draconian laws"],
    "synonyms": ["harsh", "severe", "oppressive"],
    "etymology": "源自古希腊立法者 Draco (德拉古)，其法律以严酷著称"
  },
  {
    "word": "totalitarian",
    "phonetic": "/təʊˌtælɪˈteəriən/",
    "meaning": "极权主义的",
    "pos": "adj.",
    "band": 9,
    "topic": "society",
    "example": "Totalitarian regimes systematically suppress individual freedoms and independent thought.",
    "example_cn": "极权主义政权系统性地压制个人自由和独立思想。",
    "collocations": ["totalitarian regime", "totalitarian state"],
    "synonyms": ["authoritarian", "despotic", "dictatorial"],
    "etymology": "total (全部) + -itarian → 全面控制的 → 极权主义的"
  },
  {
    "word": "apotheosis",
    "phonetic": "/əˌpɒθiˈəʊsɪs/",
    "meaning": "神化，典范",
    "pos": "n.",
    "band": 9,
    "topic": "culture",
    "example": "The novel is considered the apotheosis of modernist literature.",
    "example_cn": "这部小说被认为是现代主义文学的巅峰之作。",
    "collocations": ["apotheosis of", "reach its apotheosis"],
    "synonyms": ["pinnacle", "epitome", "culmination"],
    "etymology": "apo- (从) + theos (神) → 从凡人变为神 → 神化/典范"
  },
  {
    "word": "juxtaposition",
    "phonetic": "/ˌdʒʌkstəpəˈzɪʃən/",
    "meaning": "并列，并置",
    "pos": "n.",
    "band": 9,
    "topic": "culture",
    "example": "The juxtaposition of ancient temples alongside modern skyscrapers creates a striking visual contrast.",
    "example_cn": "古老寺庙与现代摩天大楼的并置形成了引人注目的视觉反差。",
    "collocations": ["juxtaposition of", "striking juxtaposition"],
    "synonyms": ["contrast", "comparison", "collocation"],
    "etymology": "juxta- (紧邻) + position (位置) → 紧挨着放置 → 并置"
  },
  {
    "word": "syncretism",
    "phonetic": "/ˈsɪŋkrɪtɪzəm/",
    "meaning": "融合主义",
    "pos": "n.",
    "band": 9,
    "topic": "culture",
    "example": "Religious syncretism in Southeast Asia blends Buddhist, Hindu, and indigenous spiritual practices.",
    "example_cn": "东南亚的宗教融合主义将佛教、印度教和本土精神信仰融为一体。",
    "collocations": ["cultural syncretism", "religious syncretism"],
    "synonyms": ["fusion", "amalgamation", "blending"],
    "etymology": "syn- (一起) + Krete (克里特岛) → 克里特城邦联合抵外 → 融合"
  },
  {
    "word": "philistine",
    "phonetic": "/ˈfɪlɪstaɪn/",
    "meaning": "庸人，不懂艺术的人",
    "pos": "n./adj.",
    "band": 9,
    "topic": "culture",
    "example": "He dismissed his critics as cultural philistines who could not appreciate abstract art.",
    "example_cn": "他把批评者斥为不懂抽象艺术的文化庸人。",
    "collocations": ["cultural philistine", "philistine attitude"],
    "synonyms": ["barbarian", "lowbrow", "uncultured"],
    "etymology": "源自圣经中的 Philistines (非利士人)，被视为文化粗鄙之人"
  },
  {
    "word": "esoteric",
    "phonetic": "/ˌesəˈterɪk/",
    "meaning": "深奥的，晦涩的",
    "pos": "adj.",
    "band": 9,
    "topic": "culture",
    "example": "The philosopher's esoteric writings are accessible only to those with specialised knowledge.",
    "example_cn": "这位哲学家深奥的著作只有具备专业知识的人才能理解。",
    "collocations": ["esoteric knowledge", "esoteric subject"],
    "synonyms": ["arcane", "abstruse", "recondite"],
    "etymology": "eso- (内部的) + -teric → 内部圈子才懂的 → 深奥的"
  },
  {
    "word": "archetypical",
    "phonetic": "/ˌɑːkɪˈtɪpɪkəl/",
    "meaning": "原型的，典型的",
    "pos": "adj.",
    "band": 9,
    "topic": "culture",
    "example": "The hero's journey is an archetypical narrative found in cultures across the globe.",
    "example_cn": "英雄之旅是一种在全球各种文化中都能找到的原型叙事。",
    "collocations": ["archetypical hero", "archetypical example"],
    "synonyms": ["prototypical", "quintessential", "paradigmatic"],
    "etymology": "arche- (原始) + type (类型) + -ical → 原始类型的 → 原型的"
  },
  {
    "word": "ethereal",
    "phonetic": "/ɪˈθɪəriəl/",
    "meaning": "空灵的，超凡的",
    "pos": "adj.",
    "band": 9,
    "topic": "culture",
    "example": "The ethereal quality of the music transported the audience to a transcendent state.",
    "example_cn": "音乐空灵的品质将观众带入了一种超然的状态。",
    "collocations": ["ethereal beauty", "ethereal quality"],
    "synonyms": ["celestial", "otherworldly", "sublime"],
    "etymology": "ether (以太/天空) + -eal → 如以太般的 → 空灵的"
  },
  {
    "word": "transcendental",
    "phonetic": "/ˌtrænsɛnˈdentəl/",
    "meaning": "超验的，超越的",
    "pos": "adj.",
    "band": 9,
    "topic": "culture",
    "example": "Transcendental meditation has gained popularity as a method for reducing stress and anxiety.",
    "example_cn": "超验冥想作为减轻压力和焦虑的方法越来越受欢迎。",
    "collocations": ["transcendental meditation", "transcendental experience"],
    "synonyms": ["metaphysical", "spiritual", "otherworldly"],
    "etymology": "trans- (超越) + scend (攀爬) + -ental → 超越攀爬的 → 超验的"
  },
  {
    "word": "avant-garde",
    "phonetic": "/ˌævɒ̃ˈɡɑːd/",
    "meaning": "前卫的，先锋的",
    "pos": "adj./n.",
    "band": 9,
    "topic": "culture",
    "example": "The avant-garde art movement challenged every convention of traditional aesthetic expression.",
    "example_cn": "前卫艺术运动挑战了传统审美表达的一切惯例。",
    "collocations": ["avant-garde art", "avant-garde movement"],
    "synonyms": ["experimental", "innovative", "pioneering"],
    "etymology": "法语 avant (前面) + garde (守卫) → 前卫部队 → 先锋的"
  },
  {
    "word": "paradigmatic",
    "phonetic": "/ˌpærədɪɡˈmætɪk/",
    "meaning": "范式的，典范的",
    "pos": "adj.",
    "band": 9,
    "topic": "culture",
    "example": "The Renaissance represents a paradigmatic shift in how humanity understood art and science.",
    "example_cn": "文艺复兴代表了人类理解艺术和科学方式的范式转变。",
    "collocations": ["paradigmatic shift", "paradigmatic example"],
    "synonyms": ["exemplary", "model", "archetypal"],
    "etymology": "paradigm (范式) + -atic → 关于范式的 → 范式的"
  },
  {
    "word": "mercantilism",
    "phonetic": "/ˈmɜːkəntɪlɪzəm/",
    "meaning": "重商主义",
    "pos": "n.",
    "band": 9,
    "topic": "economy",
    "example": "Mercantilism dominated European economic policy from the sixteenth to the eighteenth century.",
    "example_cn": "重商主义在十六世纪到十八世纪主导了欧洲的经济政策。",
    "collocations": ["economic mercantilism", "neo-mercantilism"],
    "synonyms": ["protectionism", "commercialism"],
    "etymology": "mercant- (商人) + -ilism (主义) → 以商人利益为主的主义 → 重商主义"
  },
  {
    "word": "autarky",
    "phonetic": "/ˈɔːtɑːki/",
    "meaning": "经济自给自足",
    "pos": "n.",
    "band": 9,
    "topic": "economy",
    "example": "North Korea's pursuit of autarky has resulted in severe economic isolation and deprivation.",
    "example_cn": "朝鲜追求经济自给自足导致了严重的经济孤立和匮乏。",
    "collocations": ["economic autarky", "pursue autarky"],
    "synonyms": ["self-sufficiency", "economic independence"],
    "etymology": "auto- (自己) + arkein (满足) → 自己满足自己 → 经济自给自足"
  },
  {
    "word": "stagflation",
    "phonetic": "/stæɡˈfleɪʃən/",
    "meaning": "滞胀",
    "pos": "n.",
    "band": 9,
    "topic": "economy",
    "example": "The 1970s oil crisis triggered a period of stagflation characterised by high inflation and stagnant growth.",
    "example_cn": "20世纪70年代的石油危机引发了一段以高通胀和经济停滞为特征的滞胀时期。",
    "collocations": ["period of stagflation", "economic stagflation"],
    "synonyms": ["inflationary stagnation", "economic malaise"],
    "etymology": "stag(nation) (停滞) + (in)flation (通胀) → 停滞加通胀 → 滞胀"
  },
  {
    "word": "plutocratic",
    "phonetic": "/ˌpluːtəˈkrætɪk/",
    "meaning": "财阀统治的",
    "pos": "adj.",
    "band": 9,
    "topic": "economy",
    "example": "Critics warn that plutocratic influence over policymaking undermines democratic governance.",
    "example_cn": "批评者警告说，财阀对政策制定的影响破坏了民主治理。",
    "collocations": ["plutocratic elite", "plutocratic influence"],
    "synonyms": ["wealth-dominated", "oligarchic"],
    "etymology": "pluto- (财富) + -cratic (统治的) → 由财富统治的 → 财阀统治的"
  },
  {
    "word": "protectionist",
    "phonetic": "/prəˈtekʃənɪst/",
    "meaning": "贸易保护主义的",
    "pos": "adj./n.",
    "band": 9,
    "topic": "economy",
    "example": "Protectionist tariffs may shield domestic industries but often provoke retaliatory trade wars.",
    "example_cn": "保护主义关税可能保护国内产业，但往往会引发报复性贸易战。",
    "collocations": ["protectionist policies", "protectionist measures"],
    "synonyms": ["isolationist", "trade-restricting"],
    "etymology": "protect (保护) + -ionist → 主张保护（国内产业）的 → 保护主义的"
  },
  {
    "word": "neoliberal",
    "phonetic": "/ˌniːəʊˈlɪbərəl/",
    "meaning": "新自由主义的",
    "pos": "adj.",
    "band": 9,
    "topic": "economy",
    "example": "Neoliberal economic reforms emphasise deregulation, privatisation, and free-market competition.",
    "example_cn": "新自由主义经济改革强调放松管制、私有化和自由市场竞争。",
    "collocations": ["neoliberal policies", "neoliberal agenda"],
    "synonyms": ["free-market", "laissez-faire", "market-oriented"],
    "etymology": "neo- (新) + liberal (自由主义的) → 新的自由主义 → 新自由主义的"
  },
  {
    "word": "deflationary",
    "phonetic": "/dɪˈfleɪʃənəri/",
    "meaning": "通货紧缩的",
    "pos": "adj.",
    "band": 9,
    "topic": "economy",
    "example": "Japan's deflationary spiral in the 1990s led to a prolonged period of economic stagnation.",
    "example_cn": "日本在20世纪90年代的通货紧缩螺旋导致了长期的经济停滞。",
    "collocations": ["deflationary pressure", "deflationary spiral"],
    "synonyms": ["price-reducing", "contractionary"],
    "etymology": "de- (减少) + flat (膨胀) + -ionary → 膨胀减少的 → 通货紧缩的"
  },
  {
    "word": "speculative",
    "phonetic": "/ˈspekjʊlətɪv/",
    "meaning": "投机的；推测性的",
    "pos": "adj.",
    "band": 9,
    "topic": "economy",
    "example": "The speculative bubble in the housing market eventually burst, triggering a global financial crisis.",
    "example_cn": "房地产市场的投机泡沫最终破裂，引发了全球金融危机。",
    "collocations": ["speculative bubble", "speculative investment"],
    "synonyms": ["conjectural", "risky", "hypothetical"],
    "etymology": "specul- (观察) + -ative → 基于观察推测的 → 投机的"
  },
  {
    "word": "asymmetric",
    "phonetic": "/ˌeɪsɪˈmetrɪk/",
    "meaning": "不对称的",
    "pos": "adj.",
    "band": 9,
    "topic": "economy",
    "example": "Asymmetric information between buyers and sellers often leads to market failure.",
    "example_cn": "买卖双方之间的信息不对称往往导致市场失灵。",
    "collocations": ["asymmetric information", "asymmetric risk"],
    "synonyms": ["uneven", "imbalanced", "disproportionate"],
    "etymology": "a- (不) + sym- (一起) + metric (测量) → 测量不一致的 → 不对称的"
  },
  {
    "word": "axiomatic",
    "phonetic": "/ˌæksiəˈmætɪk/",
    "meaning": "公理的，不言自明的",
    "pos": "adj.",
    "band": 9,
    "topic": "science",
    "example": "It is axiomatic in physics that energy can neither be created nor destroyed.",
    "example_cn": "能量既不能被创造也不能被毁灭，这在物理学中是不言自明的。",
    "collocations": ["axiomatic truth", "axiomatic principle"],
    "synonyms": ["self-evident", "unquestionable", "indisputable"],
    "etymology": "axiom (公理) + -atic → 如公理般的 → 不言自明的"
  },
  {
    "word": "stochastic",
    "phonetic": "/stəˈkæstɪk/",
    "meaning": "随机的，概率性的",
    "pos": "adj.",
    "band": 9,
    "topic": "science",
    "example": "Stochastic models are used to predict weather patterns where outcomes are inherently uncertain.",
    "example_cn": "随机模型被用于预测本质上不确定的天气模式。",
    "collocations": ["stochastic process", "stochastic model"],
    "synonyms": ["random", "probabilistic", "non-deterministic"],
    "etymology": "希腊语 stochastikos (善于猜测的) → 基于概率的 → 随机的"
  },
  {
    "word": "thermodynamic",
    "phonetic": "/ˌθɜːməʊdaɪˈnæmɪk/",
    "meaning": "热力学的",
    "pos": "adj.",
    "band": 9,
    "topic": "science",
    "example": "The thermodynamic laws governing entropy have profound implications for understanding the universe.",
    "example_cn": "支配熵的热力学定律对理解宇宙有着深远的意义。",
    "collocations": ["thermodynamic equilibrium", "thermodynamic laws"],
    "synonyms": ["thermal", "heat-energy-related"],
    "etymology": "thermo- (热) + dynamic (动力的) → 热的动力学 → 热力学的"
  },
  {
    "word": "electromagnetic",
    "phonetic": "/ɪˌlektrəʊmæɡˈnetɪk/",
    "meaning": "电磁的",
    "pos": "adj.",
    "band": 9,
    "topic": "science",
    "example": "Electromagnetic radiation from mobile phones has been the subject of extensive health research.",
    "example_cn": "手机的电磁辐射一直是广泛健康研究的主题。",
    "collocations": ["electromagnetic spectrum", "electromagnetic radiation"],
    "synonyms": ["electro-magnetic", "EM"],
    "etymology": "electro- (电) + magnetic (磁的) → 电与磁结合的 → 电磁的"
  },
  {
    "word": "photosynthetic",
    "phonetic": "/ˌfəʊtəʊsɪnˈθetɪk/",
    "meaning": "光合作用的",
    "pos": "adj.",
    "band": 9,
    "topic": "science",
    "example": "Photosynthetic efficiency varies significantly between C3 and C4 plant species.",
    "example_cn": "C3和C4植物物种之间的光合作用效率差异显著。",
    "collocations": ["photosynthetic process", "photosynthetic organisms"],
    "synonyms": ["light-synthesising", "chlorophyll-based"],
    "etymology": "photo- (光) + synthetic (合成的) → 用光来合成的 → 光合作用的"
  },
  {
    "word": "geomorphological",
    "phonetic": "/ˌdʒiːəʊˌmɔːfəˈlɒdʒɪkəl/",
    "meaning": "地貌学的",
    "pos": "adj.",
    "band": 9,
    "topic": "science",
    "example": "Geomorphological studies reveal how glacial activity shaped the landscape over millennia.",
    "example_cn": "地貌学研究揭示了冰川活动如何在数千年间塑造了地形。",
    "collocations": ["geomorphological features", "geomorphological processes"],
    "synonyms": ["landform-related", "terrain-analytical"],
    "etymology": "geo- (地球) + morph (形态) + -ological (学科的) → 研究地球形态的 → 地貌学的"
  },
  {
    "word": "paleontological",
    "phonetic": "/ˌpæliɒntəˈlɒdʒɪkəl/",
    "meaning": "古生物学的",
    "pos": "adj.",
    "band": 9,
    "topic": "science",
    "example": "Paleontological evidence suggests that mass extinctions have occurred at least five times in Earth's history.",
    "example_cn": "古生物学证据表明，地球历史上至少发生过五次大规模灭绝。",
    "collocations": ["paleontological record", "paleontological evidence"],
    "synonyms": ["fossil-related", "prehistoric"],
    "etymology": "paleo- (古) + onto (存在) + -logical (学科的) → 研究古代存在的学科 → 古生物学的"
  },
  {
    "word": "astrophysical",
    "phonetic": "/ˌæstrəʊˈfɪzɪkəl/",
    "meaning": "天体物理学的",
    "pos": "adj.",
    "band": 9,
    "topic": "science",
    "example": "Recent astrophysical observations have confirmed the existence of gravitational waves.",
    "example_cn": "最近的天体物理学观测证实了引力波的存在。",
    "collocations": ["astrophysical phenomena", "astrophysical research"],
    "synonyms": ["cosmic", "astronomical"],
    "etymology": "astro- (星) + physical (物理的) → 关于星体物理的 → 天体物理学的"
  },
  {
    "word": "ontological",
    "phonetic": "/ˌɒntəˈlɒdʒɪkəl/",
    "meaning": "本体论的",
    "pos": "adj.",
    "band": 9,
    "topic": "science",
    "example": "The ontological debate about the nature of consciousness remains unresolved in neuroscience.",
    "example_cn": "关于意识本质的本体论争论在神经科学中仍未解决。",
    "collocations": ["ontological argument", "ontological status"],
    "synonyms": ["metaphysical", "existential", "philosophical"],
    "etymology": "onto- (存在) + -logical (学科的) → 关于存在的学说 → 本体论的"
  },
  {
    "word": "epistemological",
    "phonetic": "/ɪˌpɪstɪməˈlɒdʒɪkəl/",
    "meaning": "认识论的",
    "pos": "adj.",
    "band": 9,
    "topic": "science",
    "example": "The epistemological implications of artificial intelligence challenge our understanding of knowledge itself.",
    "example_cn": "人工智能的认识论含义挑战了我们对知识本身的理解。",
    "collocations": ["epistemological framework", "epistemological question"],
    "synonyms": ["knowledge-theoretical", "cognitive-philosophical"],
    "etymology": "episteme (知识) + -ological (学科的) → 关于知识的学说的 → 认识论的"
  },
  {
    "word": "obfuscate",
    "phonetic": "/ˈɒbfʌskeɪt/",
    "meaning": "混淆，使模糊",
    "pos": "v.",
    "band": 9,
    "topic": "society",
    "example": "Politicians often obfuscate the truth to avoid accountability for their decisions.",
    "example_cn": "政客们经常混淆真相以逃避对其决策的问责。",
    "collocations": ["obfuscate the issue", "deliberately obfuscate"],
    "synonyms": ["obscure", "confuse", "muddle"],
    "etymology": "ob- (遮盖) + fusc (暗) + -ate → 使变暗 → 混淆"
  },
  {
    "word": "quantitative",
    "phonetic": "/ˈkwɒntɪtətɪv/",
    "meaning": "定量的，数量的",
    "pos": "adj.",
    "band": 9,
    "topic": "economy",
    "example": "Quantitative easing was employed by central banks worldwide to stimulate economic recovery.",
    "example_cn": "全球各国央行采用量化宽松政策来刺激经济复苏。",
    "collocations": ["quantitative easing", "quantitative analysis"],
    "synonyms": ["numerical", "measurable", "statistical"],
    "etymology": "quant- (数量) + -itative → 与数量相关的 → 定量的"
  },
  {
    "word": "pathognomonic",
    "phonetic": "/ˌpæθɒɡnəˈmɒnɪk/",
    "meaning": "特征性的，病征性的",
    "pos": "adj.",
    "band": 9,
    "topic": "health",
    "example": "Koplik spots are pathognomonic of measles, providing definitive diagnostic evidence.",
    "example_cn": "科普利克斑是麻疹的特征性表现，可提供确定性诊断依据。",
    "collocations": ["pathognomonic sign", "pathognomonic symptom"],
    "synonyms": ["diagnostic", "characteristic", "indicative"],
    "etymology": "patho- (疾病) + gnomon (判断) + -ic → 可判断疾病的 → 特征性的"
  }
]
